cli_mcp_server/__init__.py
cli_mcp_server/server.py
cli_mcp_server_fastmcp-0.2.6.dist-info/METADATA
cli_mcp_server_fastmcp-0.2.6.dist-info/WHEEL
cli_mcp_server_fastmcp-0.2.6.dist-info/entry_points.txt
cli_mcp_server_fastmcp-0.2.6.dist-info/licenses/LICENSE
cli_mcp_server_fastmcp-0.2.6.dist-info/RECORD
