Metadata-Version: 2.4
Name: cli-mcp-server-fastmcp
Version: 0.2.6
Summary: Command line interface for MCP clients with secure execution and customizable security policies
Project-URL: Homepage, https://github.com/fastmcp-me/cli-mcp-server#readme
Project-URL: Repository, https://github.com/fastmcp-me/cli-mcp-server.git
Project-URL: Issues, https://github.com/fastmcp-me/cli-mcp-server/issues
Author-email: Mladen <fangs-lever6n@icloud.com>
License-File: LICENSE
Requires-Python: >=3.10
Requires-Dist: mcp>=1.10.1
